Metadata-Version: 2.1
Name: javascriptpy
Version: 1.1.6
Summary: This package lets you use Javascript like objects in python.
Home-page: https://github.com/CodeWithSwastik/javascript-py
Author: Swas.py
Author-email: cwswas.py@gmail.com
License: UNKNOWN
Project-URL: Issue tracker, https://github.com/CodeWithSwastik/javascript-py/issues
Platform: UNKNOWN
Classifier: Programming Language :: Python :: 3
Classifier: Intended Audience :: Developers
Classifier: License :: OSI Approved :: MIT License
Classifier: Operating System :: OS Independent
Classifier: Topic :: Internet
Classifier: Topic :: Software Development :: Libraries
Classifier: Topic :: Software Development :: Libraries :: Python Modules
Classifier: Topic :: Utilities
Requires-Python: >=3.6
